ptymer/__init__.py
ptymer/_alarm.py
ptymer/_hourglass.py
ptymer/_timer.py
ptymer-0.0.1.dist-info/LICENSE
ptymer-0.0.1.dist-info/METADATA
ptymer-0.0.1.dist-info/WHEEL
ptymer-0.0.1.dist-info/top_level.txt
ptymer-0.0.1.dist-info/RECORD
