Metadata-Version: 2.1
Name: ptymer
Version: 0.0.1
Summary: Ptymer is a lightweight Python package designed to help developers manage and monitor the execution time of their code. With features like timers and countdowns, it allows you to precisely measure runtime durations and set time-based triggers. Whether you need to benchmark performance or execute actions at specific intervals, Ptymer provides a simple and efficient solution
Author-email: Caio Lima <caio-augusto@live.com>
License: MIT License
Project-URL: Homepage, https://github.com/hyskoniho/ptymer
Project-URL: Documentation, https://github.com/hyskoniho/ptymer/wiki
Project-URL: Issues, https://github.com/hyskoniho/ptymer/issues
Keywords: timer,countdown,hourglass,alarm
Classifier: Programming Language :: Python
Classifier: Programming Language :: Python :: 3
Classifier: License :: OSI Approved :: MIT License
Classifier: Operating System :: OS Independent
Requires-Python: >=3.8
License-File: LICENSE
Requires-Dist: psutil >=6.0.0
Requires-Dist: python-dateutil >=2.9.0.post0
Requires-Dist: six >=1.16.0
